{
	"backtrace" : 2,
	"backtraceGraph" : 
	{
		"commands" : 
		[
			"add_custom_target",
			"ei_add_test",
			"add_dependencies"
		],
		"files" : 
		[
			"cmake/EigenTesting.cmake",
			"test/CMakeLists.txt"
		],
		"nodes" : 
		[
			{
				"file" : 1
			},
			{
				"command" : 1,
				"file" : 1,
				"line" : 240,
				"parent" : 0
			},
			{
				"command" : 0,
				"file" : 0,
				"line" : 276,
				"parent" : 1
			},
			{
				"command" : 2,
				"file" : 0,
				"line" : 280,
				"parent" : 1
			},
			{
				"command" : 2,
				"file" : 0,
				"line" : 280,
				"parent" : 1
			},
			{
				"command" : 2,
				"file" : 0,
				"line" : 280,
				"parent" : 1
			},
			{
				"command" : 2,
				"file" : 0,
				"line" : 280,
				"parent" : 1
			},
			{
				"command" : 2,
				"file" : 0,
				"line" : 280,
				"parent" : 1
			},
			{
				"command" : 2,
				"file" : 0,
				"line" : 280,
				"parent" : 1
			}
		]
	},
	"dependencies" : 
	[
		{
			"backtrace" : 3,
			"id" : "geo_orthomethods_4::@36f028580bb02cc8272a"
		},
		{
			"backtrace" : 4,
			"id" : "geo_orthomethods_6::@36f028580bb02cc8272a"
		},
		{
			"backtrace" : 5,
			"id" : "geo_orthomethods_2::@36f028580bb02cc8272a"
		},
		{
			"backtrace" : 6,
			"id" : "geo_orthomethods_1::@36f028580bb02cc8272a"
		},
		{
			"backtrace" : 7,
			"id" : "geo_orthomethods_3::@36f028580bb02cc8272a"
		},
		{
			"backtrace" : 8,
			"id" : "geo_orthomethods_5::@36f028580bb02cc8272a"
		}
	],
	"id" : "geo_orthomethods::@36f028580bb02cc8272a",
	"name" : "geo_orthomethods",
	"paths" : 
	{
		"build" : "test",
		"source" : "test"
	},
	"sources" : [],
	"type" : "UTILITY"
}
